django_jinja_helpers/__init__.py
django_jinja_helpers/templatetags/__init__.py
django_jinja_helpers-0.2.3.dist-info/LICENSE
django_jinja_helpers-0.2.3.dist-info/METADATA
django_jinja_helpers-0.2.3.dist-info/WHEEL
django_jinja_helpers-0.2.3.dist-info/RECORD
